MANIFEST.in
README.rst
pyproject.toml
setup.py
pconway/__init__.py
pconway/__version__.py
pconway/logger.py
pconway.egg-info/PKG-INFO
pconway.egg-info/SOURCES.txt
pconway.egg-info/dependency_links.txt
pconway.egg-info/entry_points.txt
pconway.egg-info/requires.txt
pconway.egg-info/top_level.txt
pconway/clitools/__init__.py
pconway/clitools/gameoflife.py
pconway/core/__init__.py
pconway/core/custom_game.py
pconway/core/game.py
pconway/core/gameoflife.py
pconway/render/__init__.py
pconway/render/play.py
pconway/tests/__init__.py
pconway/tests/test_gameoflife.py