Metadata-Version: 2.1
Name: pconway
Version: 1.0.3
Summary: Conway's Game of Life Terminal Eye Candy implemented in Python.
Home-page: https://github.com/terrencetec/pconway
Author: TSANG Terrence Tak Lun
Author-email: terrencetec@gmail.com
License: UNKNOWN
Keywords: sample,setuptools,development
Platform: UNKNOWN
Classifier: Programming Language :: Python :: 3
Classifier: License :: OSI Approved :: MIT License
Classifier: Operating System :: OS Independent
Requires-Python: >=3.5, <4
